	[
		{
			"name": "Gatsby Blog",
			"url": "https://xenodochial-ride-0c8561.netlify.com",
			"git": "https://github.com/EricHeredia/gatsby-blog",
			"tech": ["React", "JavaScript", "HTML", "CSS", "Gatsby.js"],
	                "image": "https://github.com/EricHeredia/data-base/blob/master/thumbnails/pomodoro.png?raw=true"
		},
		{
			"name": "Pomodoro Clock",
			"url": "https://ericheredia.github.io/pomodoro-clock",
			"git": "https://github.com/EricHeredia/pomodoro-clock",
			"tech": ["React", "JavaScript", "HTML", "CSS"],
	                "image": "https://github.com/EricHeredia/data-base/blob/master/thumbnails/pomodoro.png?raw=true"
		},
                {
			"name": "Drum Machine",
			"url": "https://ericheredia.github.io/drum-machine",
			"git": "https://github.com/EricHeredia/drum-machine",
			"tech": ["React", "JavaScript", "HTML", "CSS"],
	                "image": "https://github.com/EricHeredia/data-base/blob/master/thumbnails/pomodoro.png?raw=true"
		},
                {
			"name": "JavaScript Calculator",
			"url": "https://ericheredia.github.io/javascript-calculator",
			"git": "https://github.com/EricHeredia/javascript-calculator",
			"tech": ["React", "JavaScript", "HTML", "CSS"],
	                "image": "https://github.com/EricHeredia/data-base/blob/master/thumbnails/pomodoro.png?raw=true"
		},
                {
			"name": "Markdown Previewer",
			"url": "https://codepen.io/EricHeredia/full/yQdaZx",
			"git": "https://codepen.io/EricHeredia/pen/yQdaZx",
			"tech": ["React", "JavaScript", "HTML", "CSS"],
			"codepen": true,
	                "image": "https://github.com/EricHeredia/data-base/blob/master/thumbnails/pomodoro.png?raw=true"
		},
                {
			"name": "Random Quote Machine",
			"url": "https://codepen.io/EricHeredia/full/OaGPKo",
			"git": "https://codepen.io/EricHeredia/pen/OaGPKo",
			"tech": ["React", "JavaScript", "HTML", "CSS"],
			"codepen": true,
	                "image": "https://github.com/EricHeredia/data-base/blob/master/thumbnails/pomodoro.png?raw=true"
		},
                {
			"name": "Bar Chart",
			"url": "https://ericheredia.github.io/bar-chart",
			"git": "https://github.com/EricHeredia/bar-chart",
			"tech": ["React", "JavaScript", "HTML", "CSS"],
	                "image": "https://github.com/EricHeredia/data-base/blob/master/thumbnails/pomodoro.png?raw=true"
		},
                {
			"name": "Scatter Plot",
			"url": "https://ericheredia.github.io/scatter-plot",
			"git": "https://github.com/EricHeredia/scatter-plot",
			"tech": ["React", "JavaScript", "HTML", "CSS"],
	                "image": "https://github.com/EricHeredia/data-base/blob/master/thumbnails/pomodoro.png?raw=true"
		}
	]
